setup.cfg
setup.py
utp_extensions/__init__.py
utp_extensions/base_action.py
utp_extensions/taylor.py
utp_extensions.egg-info/PKG-INFO
utp_extensions.egg-info/SOURCES.txt
utp_extensions.egg-info/dependency_links.txt
utp_extensions.egg-info/not-zip-safe
utp_extensions.egg-info/top_level.txt