Metadata-Version: 2.1
Name: utp-extensions
Version: 0.1
Summary: MBSTU upt package IUK3
Home-page: https://github.com/Fox-sys/service_installer
Author-email: berestovborisasz@gmail.com
